clios-0.6.0.dist-info/METADATA
clios-0.6.0.dist-info/WHEEL
clios-0.6.0.dist-info/entry_points.txt
clios-0.6.0.dist-info/licenses/LICENSE
clios/__init__.py
clios/cli/__init__.py
clios/cli/app.py
clios/cli/main_parser.py
clios/cli/param_parser.py
clios/cli/presenter.py
clios/cli/tokenizer.py
clios/core/__init__.py
clios/core/exceptions.py
clios/core/main_parser.py
clios/core/operator.py
clios/core/operator_fn.py
clios/core/param_info.py
clios/core/param_parser.py
clios/core/parameter.py
clios/core/tokenizer.py
clios/core/utils.py
clios/py.typed
clios-0.6.0.dist-info/RECORD
