Metadata-Version: 2.1
Name: clios
Version: 0.6.0
Summary: Create chainable command line operators
Author-Email: Prajeesh Ag <prajeeshag@gmail.com>
License: MIT License
Classifier: Programming Language :: Python :: 3
Classifier: Programming Language :: Python :: 3 :: Only
Classifier: Programming Language :: Python :: 3.12
Classifier: Programming Language :: Python :: 3.13
Classifier: Programming Language :: Python :: 3.14
Project-URL: homepage, https://prajeeshag.github.io/clios
Project-URL: repository, https://github.com/prajeeshag/clios
Project-URL: documentation, https://prajeeshag.github.io/clios
Requires-Python: <3.15,>=3.12
Requires-Dist: click==8.1.*
Requires-Dist: griffe==1.5.*
Requires-Dist: pydantic==2.12.*
Requires-Dist: rich>=13.9.4
